caneton/__init__.py
caneton/cli.py
caneton/compat.py
caneton/decode.py
caneton/exceptions.py
caneton/version.py
caneton-1.14.0.dist-info/LICENSE
caneton-1.14.0.dist-info/METADATA
caneton-1.14.0.dist-info/WHEEL
caneton-1.14.0.dist-info/entry_points.txt
caneton-1.14.0.dist-info/top_level.txt
caneton-1.14.0.dist-info/RECORD
