Metadata-Version: 2.1
Name: caneton
Version: 1.14.0
Summary: Decode CAN messages
Home-page: https://github.com/polyconseil/caneton
Author: Polyconseil
Author-email: opensource+caneton@polyconseil.fr
License: BSD-3-Clause
Keywords: CAN DBC
Platform: UNKNOWN
Classifier: Development Status :: 5 - Production/Stable
Classifier: Intended Audience :: Developers
Classifier: Natural Language :: English
Classifier: Programming Language :: Python :: 2.7
Classifier: Programming Language :: Python :: 3
